basxconnect/__init__.py
basxconnect/contributions/__init__.py
basxconnect/contributions/apps.py
basxconnect/contributions/dynamic_preferences_registry.py
basxconnect/contributions/models.py
basxconnect/contributions/settings.py
basxconnect/contributions/urls.py
basxconnect/contributions/locale/de/LC_MESSAGES/django.po
basxconnect/contributions/locale/fr/LC_MESSAGES/django.po
basxconnect/contributions/locale/nb_NO/LC_MESSAGES/django.po
basxconnect/contributions/locale/pt/LC_MESSAGES/django.po
basxconnect/contributions/locale/th/LC_MESSAGES/django.po
basxconnect/contributions/migrations/0001_initial.py
basxconnect/contributions/migrations/0002_alter_contribution_currency.py
basxconnect/contributions/migrations/0003_alter_contribution__import.py
basxconnect/contributions/migrations/0004_auto_20211030_0955.py
basxconnect/contributions/migrations/0005_alter_contribution_currency.py
basxconnect/contributions/migrations/__init__.py
basxconnect/contributions/wizards/__init__.py
basxconnect/contributions/wizards/contributionsimport.py
basxconnect/core/__init__.py
basxconnect/core/apps.py
basxconnect/core/context_processors.py
basxconnect/core/dynamic_preferences_registry.py
basxconnect/core/search_indexes.py
basxconnect/core/settings.py
basxconnect/core/urls.py
basxconnect/core/layouts/__init__.py
basxconnect/core/layouts/settings_layout.py
basxconnect/core/layouts/editperson/__init__.py
basxconnect/core/layouts/editperson/common/__init__.py
basxconnect/core/layouts/editperson/common/addresses.py
basxconnect/core/layouts/editperson/common/base_data.py
basxconnect/core/layouts/editperson/common/contributions_tab.py
basxconnect/core/layouts/editperson/common/documenttemplates_tab.py
basxconnect/core/layouts/editperson/common/head.py
basxconnect/core/layouts/editperson/common/history_tab.py
basxconnect/core/layouts/editperson/common/relationships_tab.py
basxconnect/core/layouts/editperson/common/utils.py
basxconnect/core/layouts/editperson/legalperson/__init__.py
basxconnect-0.4.62.dist-info/LICENSE
basxconnect-0.4.62.dist-info/METADATA
basxconnect-0.4.62.dist-info/WHEEL
basxconnect-0.4.62.dist-info/top_level.txt
basxconnect-0.4.62.dist-info/RECORD
