Metadata-Version: 2.1
Name: basxconnect
Version: 0.4.62
Summary: CRM application for non-profit organizations
Home-page: https://github.com/basxsoftwareassociation/basxconnect
Author: basx Software Association
Author-email: sam@basx.dev
License: New BSD License
Classifier: Development Status :: 4 - Beta
Classifier: Environment :: Console
Classifier: Environment :: Web Environment
Classifier: Intended Audience :: Developers
Classifier: License :: OSI Approved :: BSD License
Classifier: Programming Language :: Python
Classifier: Programming Language :: Python :: 3 :: Only
License-File: LICENSE
Requires-Dist: basx-bread
Requires-Dist: django-formtools ==2.3
Requires-Dist: djangorestframework
Requires-Dist: chardet
Requires-Dist: tablib
Requires-Dist: dateparser
Provides-Extra: mailer-integration
Requires-Dist: mailchimp-marketing ; extra == 'mailer-integration'
Provides-Extra: testing
Requires-Dist: basx-bread[testing] ; extra == 'testing'
